README.md
setup.cfg
setup.py
my_unique_distribution_name/Binomialdistribution.py
my_unique_distribution_name/Gaussiandistribution.py
my_unique_distribution_name/Generaldistribution.py
my_unique_distribution_name/__init__.py
my_unique_distribution_name.egg-info/PKG-INFO
my_unique_distribution_name.egg-info/SOURCES.txt
my_unique_distribution_name.egg-info/dependency_links.txt
my_unique_distribution_name.egg-info/top_level.txt