Metadata-Version: 1.2
Name: my-unique-distribution-name
Version: 0.2
Summary: A library of probability distributions
Home-page: https://example.com/distribution
Author: Latif Jan
Author-email: latifjan@example.com
License: MIT
Keywords: distributions probability
Platform: UNKNOWN
Requires-Python: >=3.6
